serverlesscli/__init__.py
serverlesscli/serverlesscli.py
serverlesscli-0.1.0.dist-info/METADATA
serverlesscli-0.1.0.dist-info/WHEEL
serverlesscli-0.1.0.dist-info/entry_points.txt
serverlesscli-0.1.0.dist-info/top_level.txt
serverlesscli-0.1.0.dist-info/RECORD
