Metadata-Version: 2.1
Name: serverlesscli
Version: 0.1.0
Summary: automate db using csv data manipulation
Home-page: UNKNOWN
Author: Raja Ram S
Author-email: rram91923@gmail.com
License: UNKNOWN
Platform: UNKNOWN
Requires-Dist: amqp ==5.2.0
Requires-Dist: APScheduler ==3.10.4
Requires-Dist: async-timeout ==4.0.3
Requires-Dist: billiard ==4.2.0
Requires-Dist: blinker ==1.7.0
Requires-Dist: click ==8.1.7
Requires-Dist: click-didyoumean ==0.3.0
Requires-Dist: click-plugins ==1.1.1
Requires-Dist: click-repl ==0.3.0
Requires-Dist: Flask ==3.0.0
Requires-Dist: itsdangerous ==2.1.2
Requires-Dist: Jinja2 ==3.1.2
Requires-Dist: kombu ==5.3.4
Requires-Dist: MarkupSafe ==2.1.3
Requires-Dist: mysql-connector-python ==8.2.0
Requires-Dist: numpy ==1.26.3
Requires-Dist: pandas ==2.1.4
Requires-Dist: prompt-toolkit ==3.0.43
Requires-Dist: protobuf ==4.21.12
Requires-Dist: PyMySQL ==1.1.0
Requires-Dist: python-crontab ==3.0.0
Requires-Dist: python-dateutil ==2.8.2
Requires-Dist: pytz ==2023.3.post1
Requires-Dist: six ==1.16.0
Requires-Dist: tzdata ==2023.4
Requires-Dist: tzlocal ==5.2
Requires-Dist: vine ==5.1.0
Requires-Dist: wcwidth ==0.2.12
Requires-Dist: Werkzeug ==3.0.1
